pyfathom/__init__.py
pyfathom/classification.py
pyfathom/classifications.py
pyfathom/classifier.py
pyfathom/matchers.py
pyfathom/rule.py
pyfathom/tokenisers.py
pyfathom-0.0.2.dist-info/LICENSE
pyfathom-0.0.2.dist-info/METADATA
pyfathom-0.0.2.dist-info/WHEEL
pyfathom-0.0.2.dist-info/top_level.txt
pyfathom-0.0.2.dist-info/RECORD
