Metadata-Version: 2.1
Name: pyfathom
Version: 0.0.2
Summary: Text comprehension library for Python
Home-page: https://github.com/jeremyorme/pyfathom
Author: Jeremy Orme
Author-email: me@jeremyorme.com
License: UNKNOWN
Platform: UNKNOWN
Classifier: Programming Language :: Python :: 3
Classifier: License :: OSI Approved :: MIT License
Classifier: Operating System :: OS Independent
